{
	"name": "Opore Gate",
	"description": "Three teleportation gates bring in the hurt. Launch starts level 52",
	"loadout": "basicNucleus",
	"baseLaunchCost": [
    	{"item": "copper", "amount": 600},
    	{"item": "lead", "amount": 600},
    	{"item": "metaglass", "amount": 200},
    	{"item": "silicon", "amount": 600},
    	{"item": "graphite", "amount": 600},
		{"item": "thorium", "amount": 600},
		{"item": "opore-mod-voidore", "amount": 600},
		{"item": "titanium", "amount": 600}
    ],
	"launchCost": [
    	{"item": "copper", "amount": 600},
    	{"item": "lead", "amount": 600},
    	{"item": "metaglass", "amount": 200},
    	{"item": "silicon", "amount": 600},
    	{"item": "graphite", "amount": 600},
		{"item": "thorium", "amount": 600},
		{"item": "opore-mod-voidore", "amount": 600},
		{"item": "titanium", "amount": 600}
    ],
    "startingItems": [
    	{"item": "copper", "amount": 600},
    	{"item": "lead", "amount": 600},
    	{"item": "metaglass", "amount": 200},
    	{"item": "silicon", "amount": 600},
    	{"item": "graphite", "amount": 600},
		{"item": "thorium", "amount": 600},
		{"item": "opore-mod-voidore", "amount": 600},
		{"item": "titanium", "amount": 600}
    ],
	"defaultStartingItems": [
    	{"item": "copper", "amount": 600},
    	{"item": "lead", "amount": 600},
    	{"item": "metaglass", "amount": 200},
    	{"item": "silicon", "amount": 600},
    	{"item": "graphite", "amount": 600},
		{"item": "thorium", "amount": 600},
		{"item": "opore-mod-voidore", "amount": 600},
		{"item": "titanium", "amount": 600}
    ],
    "conditionWave": 52,
    "launchPeriod": 5,
    "requirements": [
    	{
    		"type": "ZoneWave",
    		"zone": "TriangleOfTerror", 
    		"wave": 52
    	}
    ],
    "resources": ["copper", "lead", "coal", "sand", "titanium",  "thorium", "opore-mod-opore", "opore-mod-frazzure", "opore-mod-azurite", "opore-mod-azonite", "opore-mod-holyore", "opore-mod-voidore"]
}
